{
  "usuario": [
    {
      "id": "1",
      "nombre": "Rafu",
      "email": "rafu@gamil.com",
      "password": "1234rafuQ"
    },
    {
      "id": "2",
      "nombre": "dante",
      "email": "dante@gmail.com",
      "password": "1234dantE"
    },
    {
      "id": "3",
      "nombre": "Dante",
      "email": "mclovin@gmail.com",
      "password": "1234dantE"
    },
    {
      "id": "4",
      "nombre": "BenjaminV",
      "email": "benja@gamil.com",
      "password": "Benjamin1234"
    },
    {
      "id": "5",
      "nombre": "Franco",
      "email": "franco@gmail.com",
      "password": "Franco.1234"
    },
    {
      "id": "6",
      "nombre": "BenjminN",
      "email": "benjaminnicovani@gmail.com",
      "password": "Benjamin.1234"
    }
  ],
  "recetas": [
    {
      "id": "2482",
      "titulo": "asdasd",
      "descripcion": "asdasdasd",
      "ingredientes": "asdasdasdas"
    },
    {
      "id": "2486",
      "titulo": "Pollo Asado",
      "descripcion": "Rico Pollo Asado",
      "ingredientes": "Pollo, papa, arroz, lechuga"
    },
    {
      "id": "2487",
      "titulo": "Mandarina",
      "descripcion": "Mandarian dulce",
      "ingredientes": "mandarina"
    },
    {
      "id": 2489,
      "titulo": "Mandarina",
      "descripcion": "Mandarian dulce",
      "ingredientes": "mandarina"
    }
  ]
}